utail_base/__init__.py
utail_base/devmode_support.py
utail_base/exception_decor.py
utail_base/hangul_support.py
utail_base/log_setup.py
utail_base/net_support.py
utail_base/nlp_support.py
utail_base/selenium_pool.py
utail_base/selenium_support.py
utail_base/string_support.py
utail_base/threading_support.py
utail_base/time_support.py
utail_base/utfile_hash.py
utail_base/web_support.py
utailBase-0.0.73.dist-info/LICENSE
utailBase-0.0.73.dist-info/METADATA
utailBase-0.0.73.dist-info/WHEEL
utailBase-0.0.73.dist-info/top_level.txt
utailBase-0.0.73.dist-info/RECORD
