Metadata-Version: 2.1
Name: utailBase
Version: 0.0.73
Summary: unlimit tail basementlib
Home-page: https://...
Author: chase
Author-email: 
License: UNKNOWN
Download-URL: https://...
Keywords: utail,base
Platform: UNKNOWN
Classifier: Programming Language :: Python :: 3
Classifier: Programming Language :: Python :: 3.2
Classifier: Programming Language :: Python :: 3.3
Classifier: Programming Language :: Python :: 3.4
Classifier: Programming Language :: Python :: 3.5
Classifier: Programming Language :: Python :: 3.6
Classifier: Programming Language :: Python :: 3.7
Requires-Python: >=3
Requires-Dist: pyaml
